{
 "query_01": [
  "tname",
  "year",
  "HomeRun"
 ],
 "query_02": [
  "nameFirst",
  "nameLast",
  "birthYear",
  "birthMonth",
  "birthDay"
 ],
 "query_03": [
  "nameFirst",
  "nameLast",
  "tname"
 ],
 "query_04": [
  "teamID",
  "name",
  "yearID",
  "W", 
  "L"
 ],
 "query_05": [
  "playerID",
  "nameGiven",
  "n_pAwards"
 ],
 "query_06": [
  "playerID"
 ],
 "query_07": [
  "playerID",
  "nameFirst",
  "nameLast"
 ],
 "query_08": [
  "playerID",
  "nameFirst",
  "nameLast"
 ],
 "query_09": [
  "teamID",
  "tname",
  "yearID",
  "W"
 ],
 "query_10": [
  "teamId",
  "tname"
 ]
}